cbvfastapi/__init__.py
cbvfastapi/cbv.py
cbvfastapi-0.7.0.dist-info/METADATA
cbvfastapi-0.7.0.dist-info/WHEEL
cbvfastapi-0.7.0.dist-info/RECORD
